airflow_model-0.5.0.dist-info/licenses/LICENSE
constructors/DagConstructor.py
constructors/PostgresConstructor.py
constructors/S3Constructor.py
constructors/TaskConstructor.py
constructors/__init__.py
models/DagModel.py
models/PostgresModel.py
models/S3Model.py
models/TaskModel.py
models/__init__.py
airflow_model-0.5.0.dist-info/METADATA
airflow_model-0.5.0.dist-info/WHEEL
airflow_model-0.5.0.dist-info/top_level.txt
airflow_model-0.5.0.dist-info/RECORD
